{"_ts":[1509536569,1509579776],"_r":{"breakdown":{"html":{"bytes":[27268,21865],"requests":[6,5]},"js":{"bytes":[1004156,863645],"requests":[33,31]},"css":{"bytes":[226947,226947],"requests":[14,14]},"image":{"bytes":[8812927,10853046],"requests":[54,53]},"flash":{"bytes":[0,0],"requests":[0,0]},"font":{"bytes":[147458,167309],"requests":[6,7]},"video":{"bytes":[0,0],"requests":[0,0]},"other":{"bytes":[11167,11318],"requests":[8,8]}},"date":[1509536569,1509579776],"domElements":[803,796],"domInteractive":[2188,3584],"firstPaint":[1981,1877],"fullyLoaded":[18680,22951],"id":["171101_4W_3a087cbb51c99b6ea625945ba3ea01c0","171101_0R_057e3b5401a318f8c8e2f41366865d33"],"loadTime":[18425,22380],"render":[3859,3091],"SpeedIndex":[9568,11144],"TTFB":[426,384],"videoFrames":[[{"_i":"frame_0000.jpg","_t":0,"_vc":0},{"_i":"frame_0039.jpg","_t":3900,"_vc":32},{"_i":"frame_0049.jpg","_t":4900,"_vc":27},{"_i":"frame_0055.jpg","_t":5500,"_vc":27},{"_i":"frame_0057.jpg","_t":5700,"_vc":38},{"_i":"frame_0069.jpg","_t":6900,"_vc":54},{"_i":"frame_0134.jpg","_t":13400,"_vc":54},{"_i":"frame_0136.jpg","_t":13600,"_vc":54},{"_i":"frame_0137.jpg","_t":13700,"_vc":55},{"_i":"frame_0138.jpg","_t":13800,"_vc":56},{"_i":"frame_0140.jpg","_t":14000,"_vc":57},{"_i":"frame_0142.jpg","_t":14200,"_vc":57},{"_i":"frame_0144.jpg","_t":14400,"_vc":57},{"_i":"frame_0149.jpg","_t":14900,"_vc":99},{"_i":"frame_0161.jpg","_t":16100,"_vc":100},{"_i":"frame_0170.jpg","_t":17000,"_vc":100},{"_i":"frame_0179.jpg","_t":17900,"_vc":100},{"_i":"frame_0186.jpg","_t":18600,"_vc":100}],[{"_i":"frame_0000.jpg","_t":0,"_vc":0},{"_i":"frame_0031.jpg","_t":3100,"_vc":34},{"_i":"frame_0033.jpg","_t":3300,"_vc":32},{"_i":"frame_0042.jpg","_t":4200,"_vc":27},{"_i":"frame_0048.jpg","_t":4800,"_vc":27},{"_i":"frame_0050.jpg","_t":5000,"_vc":30},{"_i":"frame_0058.jpg","_t":5800,"_vc":54},{"_i":"frame_0134.jpg","_t":13400,"_vc":54},{"_i":"frame_0135.jpg","_t":13500,"_vc":55},{"_i":"frame_0137.jpg","_t":13700,"_vc":55},{"_i":"frame_0138.jpg","_t":13800,"_vc":55},{"_i":"frame_0139.jpg","_t":13900,"_vc":56},{"_i":"frame_0141.jpg","_t":14100,"_vc":56},{"_i":"frame_0142.jpg","_t":14200,"_vc":56},{"_i":"frame_0143.jpg","_t":14300,"_vc":56},{"_i":"frame_0144.jpg","_t":14400,"_vc":56},{"_i":"frame_0185.jpg","_t":18500,"_vc":65},{"_i":"frame_0196.jpg","_t":19600,"_vc":96},{"_i":"frame_0201.jpg","_t":20100,"_vc":99},{"_i":"frame_0206.jpg","_t":20600,"_vc":100},{"_i":"frame_0214.jpg","_t":21400,"_vc":100},{"_i":"frame_0216.jpg","_t":21600,"_vc":100},{"_i":"frame_0217.jpg","_t":21700,"_vc":100},{"_i":"frame_0225.jpg","_t":22500,"_vc":100}]],"visualComplete":[16100,20600],"lighthouse":[null,null],"pagespeed":[29,19]}}