{"_ts":[1551403193,1551446950],"_r":{"breakdown":{"html":{"bytes":[55922,56985],"requests":[10,10]},"js":{"bytes":[349910,519770],"requests":[26,30]},"css":{"bytes":[42706,42706],"requests":[5,5]},"image":{"bytes":[666655,872265],"requests":[43,45]},"flash":{"bytes":[0,0],"requests":[0,0]},"font":{"bytes":[100796,100796],"requests":[5,5]},"video":{"bytes":[0,0],"requests":[0,0]},"other":{"bytes":[840,840],"requests":[4,4]}},"date":[1551403193,1551446950],"domElements":[843,845],"domInteractive":[1624,1624],"firstPaint":[1344.5199999987,1468.9899999939],"fullyLoaded":[3994,4377],"id":["190301_K4_eb90ed426d42d2b3eda439d11c20b4af","190301_QC_805930d09a60564654c3a2e736680d8c"],"loadTime":[3459,4109],"render":[1300,1500],"SpeedIndex":[1339,1500],"TTFB":[222,267],"videoFrames":[[{"_i":"ms_000000.jpg","_t":0,"_vc":0},{"_i":"ms_001300.jpg","_t":1300,"_vc":94},{"_i":"ms_001700.jpg","_t":1700,"_vc":95},{"_i":"ms_002000.jpg","_t":2000,"_vc":100}],[{"_i":"ms_000000.jpg","_t":0,"_vc":0},{"_i":"ms_001500.jpg","_t":1500,"_vc":100}]],"visualComplete":[2000,1500],"lighthouse":[46,46],"pagespeed":[72,73]}}